mofox_plugin_dev_toolkit-0.3.1.dist-info/licenses/LICENSE
mpdt/__init__.py
mpdt/__main__.py
mpdt/cli.py
mpdt/commands/__init__.py
mpdt/commands/check.py
mpdt/commands/dev.py
mpdt/commands/generate.py
mpdt/commands/init.py
mpdt/dev/bridge_plugin/__init__.py
mpdt/dev/bridge_plugin/dev_config.py
mpdt/dev/bridge_plugin/file_watcher.py
mpdt/dev/bridge_plugin/plugin.py
mpdt/templates/__init__.py
mpdt/templates/action_template.py
mpdt/templates/adapter_template.py
mpdt/templates/chatter_template.py
mpdt/templates/event_template.py
mpdt/templates/plus_command_template.py
mpdt/templates/prompt_template.py
mpdt/templates/router_template.py
mpdt/templates/tool_template.py
mpdt/utils/__init__.py
mpdt/utils/code_parser.py
mpdt/utils/color_printer.py
mpdt/utils/config_loader.py
mpdt/utils/config_manager.py
mpdt/utils/file_ops.py
mpdt/utils/license_generator.py
mpdt/utils/plugin_parser.py
mpdt/utils/template_engine.py
mpdt/validators/__init__.py
mpdt/validators/auto_fix_validator.py
mpdt/validators/base.py
mpdt/validators/component_validator.py
mpdt/validators/config_validator.py
mpdt/validators/metadata_validator.py
mpdt/validators/structure_validator.py
mpdt/validators/style_validator.py
mpdt/validators/type_validator.py
mofox_plugin_dev_toolkit-0.3.1.dist-info/METADATA
mofox_plugin_dev_toolkit-0.3.1.dist-info/WHEEL
mofox_plugin_dev_toolkit-0.3.1.dist-info/entry_points.txt
mofox_plugin_dev_toolkit-0.3.1.dist-info/top_level.txt
mofox_plugin_dev_toolkit-0.3.1.dist-info/RECORD
