Metadata-Version: 2.4
Name: mofox-plugin-dev-toolkit
Version: 0.3.1
Summary: 开发工具集，用于快速创建、开发和测试 MoFox-Bot 插件
Author-email: MoFox-Studio <mofox.studio@example.com>
License: GPL-3.0-or-later
Project-URL: Homepage, https://github.com/MoFox-Studio/mofox-plugin-toolkit
Project-URL: Documentation, https://docs.mofox.studio/mpdt
Project-URL: Repository, https://github.com/MoFox-Studio/mofox-plugin-toolkit
Project-URL: Bug Tracker, https://github.com/MoFox-Studio/mofox-plugin-toolkit/issues
Keywords: mofox,plugin,toolkit,cli,development
Classifier: Development Status :: 3 - Alpha
Classifier: Intended Audience :: Developers
Classifier: License :: OSI Approved :: GNU General Public License v3 or later (GPLv3+)
Classifier: Programming Language :: Python :: 3
Classifier: Programming Language :: Python :: 3.11
Classifier: Programming Language :: Python :: 3.12
Requires-Python: >=3.11
License-File: LICENSE
Requires-Dist: click>=8.1.7
Requires-Dist: rich>=13.7.0
Requires-Dist: questionary>=2.0.1
Requires-Dist: jinja2>=3.1.2
Requires-Dist: toml>=0.10.2
Requires-Dist: tomli>=2.0.1
Requires-Dist: tomli-w>=1.0.0
Requires-Dist: pydantic>=2.5.0
Requires-Dist: watchdog>=3.0.0
Requires-Dist: websockets>=12.0
Requires-Dist: libcst>=1.8.6
Requires-Dist: aiohttp>=3.9.0
Requires-Dist: uvicorn>=0.24.0
Requires-Dist: fastapi>=0.104.0
Requires-Dist: ruff>=0.1.6
Requires-Dist: mypy>=1.7.0
Provides-Extra: dev
Requires-Dist: pytest>=7.4.3; extra == "dev"
Requires-Dist: pytest-cov>=4.1.0; extra == "dev"
Requires-Dist: pytest-asyncio>=0.21.1; extra == "dev"
Requires-Dist: pytest-mock>=3.12.0; extra == "dev"
Requires-Dist: mypy>=1.7.0; extra == "dev"
Requires-Dist: ruff>=0.1.6; extra == "dev"
Provides-Extra: check
Requires-Dist: mypy>=1.7.0; extra == "check"
Requires-Dist: ruff>=0.1.6; extra == "check"
Requires-Dist: bandit>=1.7.5; extra == "check"
Provides-Extra: docs
Requires-Dist: mkdocs>=1.5.3; extra == "docs"
Requires-Dist: mkdocs-material>=9.4.0; extra == "docs"
Dynamic: license-file
